trendsagi/__init__.py
trendsagi/client.py
trendsagi/exceptions.py
trendsagi/models.py
trendsagi-0.5.11.dist-info/licenses/LICENSE
trendsagi-0.5.11.dist-info/METADATA
trendsagi-0.5.11.dist-info/WHEEL
trendsagi-0.5.11.dist-info/top_level.txt
trendsagi-0.5.11.dist-info/RECORD
