Metadata-Version: 2.4
Name: trendsagi
Version: 0.5.11
Summary: The official Python client for the TrendsAGI API.
Author-email: TrendsAGI <contact@trendsagi.com>
License: MIT License
Project-URL: Homepage, https://github.com/TrendsAGI/TrendsAGI
Project-URL: Bug Tracker, https://github.com/TrendsAGI/TrendsAGI/issues
Classifier: Programming Language :: Python :: 3
Classifier: License :: OSI Approved :: MIT License
Classifier: Operating System :: OS Independent
Classifier: Intended Audience :: Developers
Classifier: Topic :: Software Development :: Libraries :: Python Modules
Requires-Python: >=3.8
License-File: LICENSE
Requires-Dist: requests>=2.28.0
Requires-Dist: pydantic>=2.0
Dynamic: license-file
